archive_all_my_mails/__init__.py
archive_all_my_mails/auth.py
archive_all_my_mails/gmail_archiver.py
archive_all_my_mails/main.py
archive_all_my_mails-0.1.0.dist-info/METADATA
archive_all_my_mails-0.1.0.dist-info/WHEEL
archive_all_my_mails-0.1.0.dist-info/entry_points.txt
archive_all_my_mails-0.1.0.dist-info/licenses/LICENSE
archive_all_my_mails-0.1.0.dist-info/RECORD
