Metadata-Version: 2.4
Name: archive-all-my-mails
Version: 0.1.0
Summary: A Python tool to archive all emails from Gmail inbox using the Gmail API
Project-URL: Homepage, https://github.com/nathanael/archive-all-my-mails
Project-URL: Repository, https://github.com/nathanael/archive-all-my-mails
Project-URL: Issues, https://github.com/nathanael/archive-all-my-mails/issues
Author: Nathan
License: MIT
License-File: LICENSE
Keywords: archive,email,gmail,google-api,productivity
Classifier: Development Status :: 4 - Beta
Classifier: Environment :: Console
Classifier: Intended Audience :: End Users/Desktop
Classifier: License :: OSI Approved :: MIT License
Classifier: Operating System :: OS Independent
Classifier: Programming Language :: Python :: 3
Classifier: Programming Language :: Python :: 3.12
Classifier: Topic :: Communications :: Email
Classifier: Topic :: Office/Business
Classifier: Topic :: Utilities
Requires-Python: >=3.12
Requires-Dist: click>=8.0.0
Requires-Dist: google-api-python-client>=2.100.0
Requires-Dist: google-auth-httplib2>=0.2.0
Requires-Dist: google-auth-oauthlib>=1.1.0
Requires-Dist: inquirer>=3.4.0
Requires-Dist: rich>=14.1.0
Provides-Extra: dev
Requires-Dist: mypy>=1.0.0; extra == 'dev'
Requires-Dist: pytest-cov>=4.0.0; extra == 'dev'
Requires-Dist: pytest>=7.0.0; extra == 'dev'
Requires-Dist: ruff>=0.1.0; extra == 'dev'
